ssladmin/middleware.py
ssladmin/__init__.py
django_ssl_admin-1.1.4.dist-info/top_level.txt
django_ssl_admin-1.1.4.dist-info/METADATA
django_ssl_admin-1.1.4.dist-info/DESCRIPTION.rst
django_ssl_admin-1.1.4.dist-info/metadata.json
django_ssl_admin-1.1.4.dist-info/WHEEL
django_ssl_admin-1.1.4.dist-info/RECORD
