Metadata-Version: 2.0
Name: django-ssl-admin
Version: 1.1.4
Summary: Django middleware to make the admin https only.
Home-page: http://dirtymonkey.co.uk/django-ssl-admin
Author: Matt Deacalion Stevens
Author-email: matt@dirtymonkey.co.uk
License: MIT
Keywords: django https secure admin ssl
Platform: UNKNOWN
Classifier: License :: OSI Approved :: MIT License
Classifier: Programming Language :: Python :: 3
Classifier: Programming Language :: Python :: 3.2
Classifier: Programming Language :: Python :: 3.3
Classifier: Programming Language :: Python :: 3.4
Classifier: Operating System :: OS Independent
Classifier: Natural Language :: English
Classifier: Development Status :: 4 - Beta
Classifier: Framework :: Django
Classifier: Environment :: Web Environment
Classifier: Intended Audience :: Developers
Classifier: Topic :: Software Development :: Libraries :: Application Frameworks
Classifier: Topic :: Internet :: WWW/HTTP :: WSGI :: Middleware
Requires-Dist: Django (>=1.6.5)
